odoo/addons/l10n_ch_mis_reports/README.rst
odoo/addons/l10n_ch_mis_reports/__init__.py
odoo/addons/l10n_ch_mis_reports/__manifest__.py
odoo/addons/l10n_ch_mis_reports/data/mis.report.csv
odoo/addons/l10n_ch_mis_reports/data/mis.report.kpi.csv
odoo/addons/l10n_ch_mis_reports/data/mis.report.style.csv
odoo/addons/l10n_ch_mis_reports/i18n/l10n_ch_mis_reports.pot
odoo/addons/l10n_ch_mis_reports/readme/CONFIGURE.rst
odoo/addons/l10n_ch_mis_reports/readme/CONTRIBUTORS.rst
odoo/addons/l10n_ch_mis_reports/readme/DESCRIPTION.rst
odoo/addons/l10n_ch_mis_reports/readme/INSTALL.rst
odoo/addons/l10n_ch_mis_reports/readme/ROADMAP.rst
odoo/addons/l10n_ch_mis_reports/readme/USAGE.rst
odoo/addons/l10n_ch_mis_reports/static/description/icon.png
odoo/addons/l10n_ch_mis_reports/static/description/index.html
odoo14_addon_l10n_ch_mis_reports-14.0.1.0.1.dev3.dist-info/METADATA
odoo14_addon_l10n_ch_mis_reports-14.0.1.0.1.dev3.dist-info/WHEEL
odoo14_addon_l10n_ch_mis_reports-14.0.1.0.1.dev3.dist-info/top_level.txt
odoo14_addon_l10n_ch_mis_reports-14.0.1.0.1.dev3.dist-info/RECORD
